textrepo/__init__.py
textrepo/client.py
textrepo_client-0.6.0.dist-info/LICENSE
textrepo_client-0.6.0.dist-info/METADATA
textrepo_client-0.6.0.dist-info/WHEEL
textrepo_client-0.6.0.dist-info/entry_points.txt
textrepo_client-0.6.0.dist-info/RECORD
