Metadata-Version: 2.1
Name: textrepo-client
Version: 0.6.0
Summary: A Python client to access a textrepo server
Home-page: https://github.com/knaw-huc/textrepo-client-python
License: MIT
Author: Bram Buitendijk
Author-email: bram.buitendijk@di.huc.knaw.nl
Requires-Python: >=3.7,<4.0
Classifier: Intended Audience :: Developers
Classifier: License :: OSI Approved :: MIT License
Classifier: Operating System :: OS Independent
Classifier: Programming Language :: Python :: 3
Classifier: Programming Language :: Python :: 3.7
Classifier: Programming Language :: Python :: 3.8
Classifier: Programming Language :: Python :: 3.9
Classifier: Programming Language :: Python :: 3.10
Classifier: Programming Language :: Python :: 3.11
Classifier: Programming Language :: Python :: 3.12
Requires-Dist: dataclasses-json (>=0.6.7,<0.7.0)
Requires-Dist: marshmallow (>=3.15.0,<4.0.0)
Requires-Dist: python-dateutil (>=2.8.1,<3.0.0)
Requires-Dist: requests (>=2.27.1,<3.0.0)
Project-URL: Bug Tracker, https://github.com/knaw-huc/textrepo-client-python/issues
Project-URL: Repository, https://github.com/knaw-huc/textrepo-client-python
